[
  {
    "link": "https://multimedia.bbycastatic.ca/multimedia/products/500x500/156/15657/15657623.jpg",
    "name": "Dell 23.6 FHD 165Hz 4ms GTG Curved VA LED FreeSync Gaming Monitor",
    "price": "$399.99",
    "type": "Display"
  },
  {
    "link": "https://multimedia.bbycastatic.ca/multimedia/products/500x500/146/14611/14611307.jpg",
    "name": "Samsung 32 FHD 75Hz 4ms GTG Curved VA LED FreeSync Gaming Monitor",
    "price": "$249.99",
    "type": "Display"
  },
  {
    "link": "https://multimedia.bbycastatic.ca/multimedia/products/500x500/149/14933/14933348.jpg",
    "name": "Samsung 27 FHD 75Hz 5ms GTG IPS LED FreeSync Gaming Monitor",
    "price": "$249.99",
    "type": "Display"
  },
  {
    "link": "https://multimedia.bbycastatic.ca/multimedia/products/500x500/158/15852/15852555.jpg",
    "name": "Acer 31.5 FHD 165Hz 1ms GTG Curved VA LED FreeSync Gaming Monitor",
    "price": "$399.99",
    "type": "Display"
  },
  {
    "link": "https://multimedia.bbycastatic.ca/multimedia/products/500x500/149/14933/14933347.jpg",
    "name": "Samsung 24 FHD 75Hz 5ms GTG IPS LED FreeSync Gaming Monitor",
    "price": "$249.99",
    "type": "Display"
  },
  {
    "link": "https://multimedia.bbycastatic.ca/multimedia/products/500x500/157/15732/15732100.jpg",
    "name": "Acer 23.8 FHD 75Hz 1ms GTG VA LED Monitor (KA242Y ABI) - Black",
    "price": "$199.99",
    "type": "Display"
  },
  {
    "link": "https://multimedia.bbycastatic.ca/multimedia/products/500x500/138/13819/13819627.jpg",
    "name": "ASUS 24 FHD 165Hz 0.5ms GTG TN LED G-Sync Gaming Monitor",
    "price": "$269.99",
    "type": "Display"
  },

  {
    "link": "https://multimedia.bbycastatic.ca/multimedia/products/500x500/157/15701/15701050.jpg",
    "name": "ASUS TUF 27 QHD 170Hz 1ms GTG IPS LED G-Sync Monitor",
    "price": "$469.99",
    "type": "Display"
  },
  {
    "link": "https://multimedia.bbycastatic.ca/multimedia/products/500x500/149/14936/14936662.jpg",
    "name": "Dell 24 FHD 75Hz 4ms GTG IPS LED FreeSync Gaming Monitor",
    "price": "$199.99",
    "type": "Display"
  }
]

  